setup.cfg
setup.py
opencw/task_final.py
opencw/task_step_1.py
opencw/task_step_2.py
opencw/task_step_3.py
opencw/task_with_comment.py
opencw.egg-info/PKG-INFO
opencw.egg-info/SOURCES.txt
opencw.egg-info/dependency_links.txt
opencw.egg-info/not-zip-safe
opencw.egg-info/top_level.txt