Metadata-Version: 2.1
Name: opencw
Version: 0.1
Summary: Computer vision 
Author-email: a.s.ulmasov@yandex.ru
